CHANGELOG.txt
LICENSE.txt
MANIFEST.in
README.txt
setup.py
hammingambuj/__init__.py
hammingambuj/hammingcode.py
hammingambuj.egg-info/PKG-INFO
hammingambuj.egg-info/SOURCES.txt
hammingambuj.egg-info/dependency_links.txt
hammingambuj.egg-info/top_level.txt
test_cases/1generate_hamming_code_for_101_binary_data.py
test_cases/2generate_hamming_code_for_102_integer_type_data_Negative.py
test_cases/3generate_hamming_code_for_long_binary_data.py
test_cases/4detect_zero_bit_error_in_hamming_code.py
test_cases/5detect_single_bit_error_in_hamming_code.py
test_cases/6detect_multiple_bit_error_in_hamming_code.py
test_cases/7detect_error_in_long_length_hamming_code.py
test_cases/8detect_error_in_non_binary_hamming_code_Negative.py
test_cases/9detect_error_in_integer_type_hamming_code_Negative.py